peco/.gitignore
peco/LICENSE
peco/README.md
peco/__init__.py
peco/cut.py
peco/cut.pyi
peco/peco.py
peco/peco.pyi
peco/py.typed
pecolib-0.0.2.dist-info/METADATA
pecolib-0.0.2.dist-info/WHEEL
pecolib-0.0.2.dist-info/licenses/LICENSE
pecolib-0.0.2.dist-info/RECORD
