Metadata-Version: 2.4
Name: pecolib
Version: 0.0.2
Summary: Tiny parser combinators library
Project-URL: Homepage, https://github.com/true-grue/peco
Project-URL: Issues, https://github.com/true-grue/peco/issues
Author-email: Peter Sovietov <peter.sovietov@gmail.com>
License-Expression: MIT
License-File: LICENSE
Classifier: Operating System :: OS Independent
Classifier: Programming Language :: Python :: 3
Requires-Python: >=3.10
